adorable/__init__.py
adorable/_palette.py
adorable/ansi.py
adorable/color.py
adorable/markup.py
adorable/py.typed
adorable/style.py
adorable/stylesheet.py
adorable/term.py
adorable/utils.py
adorable/webcolors.py
adorable-0.1.6.dist-info/licenses/LICENSE
adorable-0.1.6.dist-info/METADATA
adorable-0.1.6.dist-info/WHEEL
adorable-0.1.6.dist-info/top_level.txt
adorable-0.1.6.dist-info/RECORD
