Metadata-Version: 2.4
Name: adorable
Version: 0.1.6
Summary: Make Text Adorable
License: MIT License
Project-URL: Documentation, https://phoenixr-codes.github.io/adorable/
Project-URL: Source Code, https://github.com/phoenixr-codes/adorable/
Keywords: ansi,color,colour,console,style,terminal
Classifier: Development Status :: 6 - Mature
Classifier: Intended Audience :: Developers
Classifier: License :: OSI Approved :: MIT License
Classifier: Natural Language :: English
Classifier: Programming Language :: Python
Classifier: Topic :: Software Development :: User Interfaces
Classifier: Topic :: Text Processing
Classifier: Typing :: Typed
Requires-Python: >=3.9
License-File: LICENSE
Provides-Extra: dev
Requires-Dist: mypy; extra == "dev"
Requires-Dist: pytest; extra == "dev"
Requires-Dist: tox; extra == "dev"
Provides-Extra: docs
Requires-Dist: furo>=2022.12.07; extra == "docs"
Requires-Dist: Sphinx>=6.0.0; extra == "docs"
Requires-Dist: sphinx_copybutton; extra == "docs"
Requires-Dist: sphinx_inline_tabs; extra == "docs"
Requires-Dist: sphinxcontrib-repl; extra == "docs"
Requires-Dist: sphinxcontrib-spelling; extra == "docs"
Requires-Dist: sphinxemoji; extra == "docs"
Dynamic: license-file
